Metadata-Version: 2.1
Name: astra-python
Version: 0.1.2
Summary: Python SDK for the Astra API.
Home-page: https://github.com/AstraFinance/astra-python
Author: Astra, Inc.
Author-email: gil@astra.finance
License: MIT
Keywords: api,client,astra,plaid,dwolla
Platform: UNKNOWN
Classifier: Programming Language :: Python
Classifier: License :: OSI Approved :: MIT License
Classifier: Topic :: Software Development :: Libraries :: Python Modules
Classifier: Operating System :: OS Independent
Requires-Python: >=2.7
